qpsphere/__init__.py
qpsphere/_version.py
qpsphere/_version_save.py
qpsphere/cnvnc.py
qpsphere/edgefit.py
qpsphere/util.py
qpsphere/imagefit/__init__.py
qpsphere/imagefit/alg.py
qpsphere/imagefit/interp.py
qpsphere/models/__init__.py
qpsphere/models/excpt.py
qpsphere/models/mod_mie.py
qpsphere/models/mod_mie_avg.py
qpsphere/models/mod_proj.py
qpsphere/models/mod_rytov.py
qpsphere/models/mod_rytov_sc.py
qpsphere/models/_bhfield/__init__.py
qpsphere/models/_bhfield/fetch.py
qpsphere/models/_bhfield/wrap.py
qpsphere/resources/bhfield-arp.exe
qpsphere/resources/bhfield-std.exe
qpsphere/resources/shipped_resources_go_here
qpsphere-0.5.9.dist-info/LICENSE
qpsphere-0.5.9.dist-info/METADATA
qpsphere-0.5.9.dist-info/WHEEL
qpsphere-0.5.9.dist-info/top_level.txt
qpsphere-0.5.9.dist-info/RECORD
