Metadata-Version: 2.1
Name: qpsphere
Version: 0.5.9
Summary: library for analyzing spherical objects in phase imaging
Home-page: https://github.com/RI-imaging/qpsphere
Author: Paul Müller
Author-email: dev@craban.de
License: MIT
Keywords: digital holographic microscopy,optics,quantitative phase imaging,refractive index,scattering
Platform: ALL
Classifier: Operating System :: OS Independent
Classifier: Programming Language :: Python :: 3
Classifier: Intended Audience :: Science/Research
Requires-Python: >=3.6, <4
Requires-Dist: appdirs
Requires-Dist: h5py (>=2.7.0)
Requires-Dist: lmfit
Requires-Dist: nrefocus (>=0.1.5)
Requires-Dist: numpy (>=1.12.0)
Requires-Dist: scikit-image (>=0.11.0)
Requires-Dist: scipy (>=0.18.0)
Requires-Dist: qpimage (>=0.6.1)
